gitops_kubernetes/__init__.py
gitops_kubernetes/pkg_version.py
gitops_kubernetes-0.1.3.dist-info/WHEEL
gitops_kubernetes-0.1.3.dist-info/METADATA
gitops_kubernetes-0.1.3.dist-info/RECORD
