Metadata-Version: 2.1
Name: gitops-kubernetes
Version: 0.1.3
Summary: Implementa GitOps com Kubernetes
Home-page: https://github.com/e5r/gitops-kubernetes
License: Apache-2.0
Keywords: git,kubernetes,gitops,devops,e5r
Author: E5R Development Team
Maintainer: Erlimar Silva Campos
Maintainer-email: erlimar@gmail.com
Requires-Python: >=3.10,<4.0
Classifier: Development Status :: 2 - Pre-Alpha
Classifier: Intended Audience :: Information Technology
Classifier: Intended Audience :: System Administrators
Classifier: License :: OSI Approved :: Apache Software License
Classifier: Natural Language :: Portuguese (Brazilian)
Classifier: Operating System :: OS Independent
Classifier: Programming Language :: Python :: 3
Classifier: Programming Language :: Python :: 3.10
Classifier: Topic :: Software Development
Classifier: Topic :: Software Development :: Build Tools
Classifier: Topic :: Software Development :: Libraries
Classifier: Topic :: Software Development :: Libraries :: Python Modules
Classifier: Topic :: System :: Clustering
Classifier: Topic :: System :: Distributed Computing
Classifier: Topic :: System :: Installation/Setup
Classifier: Topic :: System :: Software Distribution
Classifier: Topic :: System :: Systems Administration
Classifier: Topic :: Utilities
Project-URL: Documentation, https://github.com/e5r/gitops-kubernetes
Project-URL: Repository, https://github.com/e5r/gitops-kubernetes
